gamee/__init__.py
gamee/__main__.py
gamee-0.0.2.dist-info/License
gamee-0.0.2.dist-info/METADATA
gamee-0.0.2.dist-info/WHEEL
gamee-0.0.2.dist-info/top_level.txt
gamee-0.0.2.dist-info/RECORD
