Metadata-Version: 2.1
Name: gamee
Version: 0.0.2
Summary: Experimental gamee hack
Home-page: https://t.me/execal
Author: Zarox
Author-email: mineiszarox@gmail.com
License: MIT
Project-URL: Bug Tracker, https://t.me/zarox
Keywords: python,gamee,hack
Classifier: Programming Language :: Python :: 3
Classifier: License :: OSI Approved :: MIT License
Classifier: Operating System :: OS Independent
Requires-Python: >=3.5
License-File: License
Requires-Dist: requests
